pyrdt/__init__.py
pyrdt/atom.py
pyrdt/combo.py
pyrdt/math.py
pyrdt/stat.py
pywfz/__init__.py
pywfz/myMath.py
pywfz/sql.py
pywfz/util.py
saveCustomer/__init__.py
saveCustomer/saveCustomer.py
saveCustomer-1.0.5.dist-info/LICENSE
saveCustomer-1.0.5.dist-info/METADATA
saveCustomer-1.0.5.dist-info/WHEEL
saveCustomer-1.0.5.dist-info/top_level.txt
saveCustomer-1.0.5.dist-info/RECORD
